haedream/__init__.py
haedream/__version__.py
haedream/saveLog.py
haedream-0.0.9.dist-info/METADATA
haedream-0.0.9.dist-info/WHEEL
haedream-0.0.9.dist-info/top_level.txt
haedream-0.0.9.dist-info/RECORD
