Metadata-Version: 2.1
Name: haedream
Version: 0.0.9
Summary: This is a package for haedream
Home-page: https://github.com/Gosegu2024/Haedream.git
Author: GOSEGU
Author-email: jhj990203@gmail.com
Classifier: Programming Language :: Python :: 3
Classifier: License :: OSI Approved :: MIT License
Classifier: Operating System :: OS Independent
Requires-Python: >=3.6
